ImageTools/__init__.py
ImageToolsMadeEasy-2019.12.30.dist-info/LICENSE
ImageToolsMadeEasy-2019.12.30.dist-info/METADATA
ImageToolsMadeEasy-2019.12.30.dist-info/WHEEL
ImageToolsMadeEasy-2019.12.30.dist-info/top_level.txt
ImageToolsMadeEasy-2019.12.30.dist-info/RECORD
