Metadata-Version: 2.1
Name: ImageToolsMadeEasy
Version: 2019.12.30
Summary: Tools to simplify using face detection and ArUco recognition with PIL image objects
Home-page: https://github.com/paulbaumgarten/ImageToolsMadyEasy
Author: Paul Baumgarten
Author-email: pbaumgarten@gmail.com
License: UNKNOWN
Keywords: PIL pillow opencv aruco haarcascades
Platform: UNKNOWN
Classifier: Programming Language :: Python :: 3
Classifier: License :: OSI Approved :: MIT License
Classifier: Operating System :: OS Independent
Requires-Python: >=3
Requires-Dist: numpy
Requires-Dist: opencv-contrib-python
Requires-Dist: pillow
